{
  "version": "0.0.1",
  "lastUpdated": "2025-06-30T10:13:49.549Z",
  "data": [
    {
      "idp": "22287",
      "title": "Propunere legislativă pentru modificarea şi completarea Legii nr.47/1992 privind organizarea şi funcţionarea Curţii Constituţionale, cu modificările şi completările ulterioareDerularea procedurii legislative",
      "registrationNumber": {
        "bpi": "87/01-04-2025",
        "deputyChamber": "95/02.04.2025",
        "senateChamber": "B37/2025"
      },
      "legislativeProcedure": "cf. Constitutiei revizuita în 2003",
      "decidingChamber": "Senatul",
      "type": "Propunere legislativa\npentru\nmodificarea\nL. nr.\n47/1992",
      "emergencyProcedure": false,
      "status": {
        "short": "pe ordinea de zi",
        "long": "pe ordinea de zi a sedintelor Camerei Deputatilor"
      },
      "initiators": [
        "62",
        "70",
        "103",
        "246",
        "318",
        "158",
        "137",
        "21",
        "50",
        "67",
        "75",
        "101",
        "128",
        "152",
        "148",
        "169",
        "175",
        "218",
        "231",
        "237",
        "304",
        "312",
        "319",
        "323"
      ],
      "publicConsultation": {
        "dueDate": "2025-04-30T00:00:00.000Z",
        "count": 0
      },
      "documents": [
        {
          "textUrl": "https://www.cdep.ro/proiecte/2025/000/90/5/em87.pdf",
          "title": "Expunerea de motive"
        },
        {
          "textUrl": "https://www.cdep.ro/proiecte/2025/000/90/5/pl87.pdf",
          "title": "Forma iniţiatorului"
        },
        {
          "textUrl": "https://www.cdep.ro/proiecte/2025/000/90/5/ces87.pdf",
          "title": "Avizul Consiliului Economic şi Social"
        },
        {
          "textUrl": "https://www.cdep.ro/proiecte/2025/000/90/5/cl87.pdf",
          "title": "Avizul Consiliului Legislativ"
        }
      ],
      "url": "https://www.cdep.ro//pls/proiecte/upl_pck2015.proiect?idp=22287"
    },
    {
      "idp": "22358",
      "title": "Propunere legislativă pentru modificarea şi completarea Legii nr.370/2004 pentru alegerea Preşedintelui României, republicatăDerularea procedurii legislative",
      "registrationNumber": {
        "bpi": "160/14-05-2025",
        "deputyChamber": "154/20.05.2025",
        "senateChamber": "L81/2025"
      },
      "legislativeProcedure": "cf. Constitutiei revizuita în 2003",
      "decidingChamber": "Camera Deputaţilor",
      "type": "Propunere legislativa\npentru\nmodificarea\nL. nr.\n370/2004",
      "emergencyProcedure": false,
      "status": {
        "short": "la comisii",
        "long": "trimis pentru raport la comisiile permanente ale Camerei Deputatilor"
      },
      "initiators": [
        "62",
        "70",
        "103",
        "246",
        "318",
        "158",
        "137",
        "21",
        "50",
        "67",
        "75",
        "101",
        "128",
        "152",
        "148",
        "169",
        "175",
        "218",
        "231",
        "237",
        "304",
        "312",
        "319",
        "323"
      ],
      "publicConsultation": "",
      "documents": [
        {
          "textUrl": "https://www.cdep.ro/proiecte/2025/100/50/4/as160.pdf",
          "title": "Adresa Senatului"
        },
        {
          "textUrl": "https://www.cdep.ro/proiecte/2025/100/50/4/in160.pdf",
          "title": "Adresa iniţiatorului"
        },
        {
          "textUrl": "https://www.cdep.ro/proiecte/2025/100/50/4/em160.pdf",
          "title": "Expunerea de motive"
        },
        {
          "textUrl": "https://www.cdep.ro/proiecte/2025/100/50/4/pl160.pdf",
          "title": "Forma iniţiatorului"
        },
        {
          "textUrl": "https://www.cdep.ro/proiecte/2025/100/50/4/cl160.pdf",
          "title": "Avizul Consiliului Legislativ"
        },
        {
          "textUrl": "https://www.cdep.ro/proiecte/2025/100/50/4/pvg160.pdf",
          "title": "Punctul de vedere al Guvernului"
        },
        {
          "textUrl": "https://www.cdep.ro/proiecte/2025/100/50/4/csm160.pdf",
          "title": "Avizul Consiliului Superior al Magistraturii"
        },
        {
          "textUrl": "https://www.cdep.ro/proiecte/2025/100/50/4/aep160.pdf",
          "title": "Avizul Autorității Electorale Permanente"
        }
      ],
      "url": "https://www.cdep.ro//pls/proiecte/upl_pck2015.proiect?idp=22358"
    },
    {
      "idp": "22395",
      "title": "Propunere legislativă privind declararea Zilei de 5 octombrie ca \"Ziua Drepturilor Electorale\"Derularea procedurii legislative",
      "registrationNumber": {
        "bpi": "204/03-06-2025",
        "deputyChamber": "183/04.06.2025",
        "senateChamber": "L119/2025"
      },
      "legislativeProcedure": "cf. Constitutiei revizuita în 2003",
      "decidingChamber": "Camera Deputaţilor",
      "type": "Propunere legislativa",
      "emergencyProcedure": false,
      "status": {
        "short": "la comisii",
        "long": "trimis pentru raport la comisiile permanente ale Camerei Deputatilor"
      },
      "initiators": [
        "62",
        "70",
        "103",
        "246",
        "318",
        "158",
        "137",
        "21",
        "50",
        "67",
        "75",
        "101",
        "128",
        "152",
        "148",
        "169",
        "175",
        "218",
        "231",
        "237",
        "304",
        "312",
        "319",
        "323"
      ],
      "publicConsultation": "",
      "documents": [
        {
          "textUrl": "https://www.cdep.ro/proiecte/2025/100/80/3/em204.pdf",
          "title": "Expunerea de motive"
        },
        {
          "textUrl": "https://www.cdep.ro/proiecte/2025/100/80/3/pl204.pdf",
          "title": "Forma iniţiatorului"
        },
        {
          "textUrl": "https://www.cdep.ro/proiecte/2025/100/80/3/ces204.pdf",
          "title": "Avizul Consiliului Economic şi Social"
        },
        {
          "textUrl": "https://www.cdep.ro/proiecte/2025/100/80/3/cl204.pdf",
          "title": "Avizul Consiliului Legislativ"
        }
      ],
      "url": "https://www.cdep.ro//pls/proiecte/upl_pck2015.proiect?idp=22395"
    },
    {
      "idp": "22396",
      "title": "Propunere legislativă privind utilizarea responsabilă a inteligenţei artificialeDerularea procedurii legislative",
      "registrationNumber": {
        "bpi": "205/03-06-2025",
        "deputyChamber": "184/04.06.2025",
        "senateChamber": "L140/2025"
      },
      "legislativeProcedure": "cf. Constitutiei revizuita în 2003",
      "decidingChamber": "Camera Deputaţilor",
      "type": "Propunere legislativa",
      "emergencyProcedure": false,
      "status": {
        "short": "la comisii",
        "long": "trimis pentru raport la comisiile permanente ale Camerei Deputatilor"
      },
      "initiators": [
        "70",
        "103",
        "246",
        "158",
        "50",
        "75",
        "101",
        "128",
        "152",
        "175",
        "218",
        "231",
        "304",
        "323"
      ],
      "publicConsultation": "",
      "documents": [
        {
          "textUrl": "https://www.cdep.ro/proiecte/2025/100/80/4/em205.pdf",
          "title": "Expunerea de motive"
        },
        {
          "textUrl": "https://www.cdep.ro/proiecte/2025/100/80/4/pl205.pdf",
          "title": "Forma iniţiatorului"
        },
        {
          "textUrl": "https://www.cdep.ro/proiecte/2025/100/80/4/ces205.pdf",
          "title": "Avizul Consiliului Economic şi Social"
        },
        {
          "textUrl": "https://www.cdep.ro/proiecte/2025/100/80/4/cl205.pdf",
          "title": "Avizul Consiliului Legislativ"
        },
        {
          "textUrl": "https://www.cdep.ro/proiecte/2025/100/80/4/ancom205.pdf",
          "title": "Avizul ANCOM"
        },
        {
          "textUrl": "https://www.cdep.ro/proiecte/2025/100/80/4/cna205.pdf",
          "title": "Avizul Consiliului Național al Audiovizualului"
        }
      ],
      "url": "https://www.cdep.ro//pls/proiecte/upl_pck2015.proiect?idp=22396"
    },
    {
      "idp": "22401",
      "title": "Propunere legislativă pentru modificarea art.2 alin.(2) din Legea nr.153/2017 privind salarizarea personalului plătit din fonduri publiceDerularea procedurii legislative",
      "registrationNumber": {
        "bpi": "210/04-06-2025",
        "deputyChamber": "BP210/04.06.2025"
      },
      "legislativeProcedure": "cf. Constitutiei revizuita în 2003",
      "decidingChamber": "Camera Deputaţilor",
      "type": "Propunere legislativa\npentru\nmodificarea\nL. nr.\n153/2017",
      "emergencyProcedure": false,
      "status": {
        "short": "la senat",
        "long": "la Senat"
      },
      "initiators": [
        "3",
        "62",
        "103",
        "246",
        "318",
        "13",
        "15",
        "16",
        "27",
        "33",
        "60",
        "69",
        "72",
        "99",
        "100",
        "108",
        "119",
        "134",
        "137",
        "173",
        "200",
        "211",
        "215",
        "221",
        "228",
        "235",
        "255",
        "258",
        "301",
        "315",
        "321",
        "67",
        "75",
        "101",
        "128",
        "152",
        "169",
        "175",
        "218",
        "237",
        "304",
        "312",
        "319",
        "257"
      ],
      "publicConsultation": "",
      "documents": [
        {
          "textUrl": "https://www.cdep.ro/proiecte/bp/2025/200/10/0/in210.pdf",
          "title": "Adresa iniţiatorului"
        },
        {
          "textUrl": "https://www.cdep.ro/proiecte/bp/2025/200/10/0/em210.pdf",
          "title": "Expunerea de motive"
        },
        {
          "textUrl": "https://www.cdep.ro/proiecte/bp/2025/200/10/0/pl210.pdf",
          "title": "Forma iniţiatorului"
        }
      ],
      "url": "https://www.cdep.ro//pls/proiecte/upl_pck2015.proiect?idp=22401"
    },
    {
      "idp": "22400",
      "title": "Propunere legislativă privind reglementarea şi interzicerea dispozitivelor electronice pentru vapare de unică folosinţăDerularea procedurii legislative",
      "registrationNumber": {
        "bpi": "209/04-06-2025",
        "deputyChamber": "BP209/04.06.2025"
      },
      "legislativeProcedure": "cf. Constitutiei revizuita în 2003",
      "decidingChamber": "Camera Deputaţilor",
      "type": "Propunere legislativa",
      "emergencyProcedure": false,
      "status": {
        "short": "la senat",
        "long": "la Senat"
      },
      "initiators": [
        "62",
        "103",
        "246",
        "318",
        "67",
        "75",
        "101",
        "128",
        "152",
        "148",
        "169",
        "175",
        "218",
        "231",
        "237",
        "304",
        "312",
        "319",
        "323",
        "132"
      ],
      "publicConsultation": "",
      "documents": [
        {
          "textUrl": "https://www.cdep.ro/proiecte/bp/2025/200/00/9/in209.pdf",
          "title": "Adresa iniţiatorului"
        },
        {
          "textUrl": "https://www.cdep.ro/proiecte/bp/2025/200/00/9/em209.pdf",
          "title": "Expunerea de motive"
        },
        {
          "textUrl": "https://www.cdep.ro/proiecte/bp/2025/200/00/9/pl209.pdf",
          "title": "Forma iniţiatorului"
        }
      ],
      "url": "https://www.cdep.ro//pls/proiecte/upl_pck2015.proiect?idp=22400"
    },
    {
      "idp": "22404",
      "title": "Propunere legislativă privind modificarea şi completarea Legii nr.192/2006 privind medierea şi organizarea profesiei de mediator şi pentru completarea Legii nr.51/1995 pentru organizarea şi exercitarea profesiei de avocatDerularea procedurii legislative",
      "registrationNumber": {
        "bpi": "213/11-06-2025",
        "deputyChamber": "BP213/11.06.2025"
      },
      "legislativeProcedure": "cf. Constitutiei revizuita în 2003",
      "decidingChamber": "Camera Deputaţilor",
      "type": "Propunere legislativa",
      "emergencyProcedure": false,
      "status": {
        "short": "la senat",
        "long": "la Senat"
      },
      "initiators": [
        "103",
        "246",
        "280",
        "33",
        "60",
        "89",
        "99",
        "108",
        "144",
        "154",
        "201",
        "215",
        "235",
        "262",
        "263",
        "315",
        "321",
        "325",
        "50",
        "67",
        "75",
        "101",
        "128",
        "152",
        "148",
        "175",
        "218",
        "231",
        "237",
        "304",
        "312",
        "319",
        "323",
        "55",
        "65",
        "77",
        "132",
        "183",
        "229",
        "250",
        "257"
      ],
      "publicConsultation": "",
      "documents": [
        {
          "textUrl": "https://www.cdep.ro/proiecte/bp/2025/200/10/3/in213.pdf",
          "title": "Adresa iniţiatorului"
        },
        {
          "textUrl": "https://www.cdep.ro/proiecte/bp/2025/200/10/3/em213.pdf",
          "title": "Expunerea de motive"
        },
        {
          "textUrl": "https://www.cdep.ro/proiecte/bp/2025/200/10/3/pl213.pdf",
          "title": "Forma iniţiatorului"
        }
      ],
      "url": "https://www.cdep.ro//pls/proiecte/upl_pck2015.proiect?idp=22404"
    },
    {
      "idp": "22364",
      "title": "Propunere legislativă pentru modificarea Legii nr.33/2007 privind organizarea şi desfăşurarea alegerilor pentru Parlamentul EuropeanDerularea procedurii legislative",
      "registrationNumber": {
        "bpi": "166/21-05-2025",
        "deputyChamber": "BP166/21.05.2025"
      },
      "legislativeProcedure": "cf. Constitutiei revizuita în 2003",
      "decidingChamber": "Camera Deputaţilor",
      "type": "Propunere legislativa\npentru\nmodificarea\nL. nr.\n33/2007\nmodificarea\nL. nr.\n22/2007",
      "emergencyProcedure": false,
      "status": {
        "short": "la senat",
        "long": "la Senat"
      },
      "initiators": [
        "3",
        "5",
        "70",
        "86",
        "103",
        "135",
        "246",
        "251",
        "137",
        "21",
        "50",
        "67",
        "101",
        "128",
        "152",
        "148",
        "175",
        "218",
        "231",
        "237",
        "304",
        "312",
        "319",
        "323",
        "55"
      ],
      "publicConsultation": "",
      "documents": [
        {
          "textUrl": "https://www.cdep.ro/proiecte/bp/2025/100/60/6/in166.pdf",
          "title": "Adresa iniţiatorului"
        },
        {
          "textUrl": "https://www.cdep.ro/proiecte/bp/2025/100/60/6/em166.pdf",
          "title": "Expunerea de motive"
        },
        {
          "textUrl": "https://www.cdep.ro/proiecte/bp/2025/100/60/6/pl166.pdf",
          "title": "Forma iniţiatorului"
        }
      ],
      "url": "https://www.cdep.ro//pls/proiecte/upl_pck2015.proiect?idp=22364"
    },
    {
      "idp": "22365",
      "title": "Propunere legislativă pentru modificarea art.4 alin.(2) din Legea 370/2004 pentru alegerea Preşedintelui RomânieiDerularea procedurii legislative",
      "registrationNumber": {
        "bpi": "167/21-05-2025",
        "deputyChamber": "BP167/21.05.2025"
      },
      "legislativeProcedure": "cf. Constitutiei revizuita în 2003",
      "decidingChamber": "Camera Deputaţilor",
      "type": "Propunere legislativa\npentru\nmodificarea\nL. nr.\n370/2004",
      "emergencyProcedure": false,
      "status": {
        "short": "la senat",
        "long": "la Senat"
      },
      "initiators": [
        "3",
        "5",
        "62",
        "70",
        "86",
        "103",
        "135",
        "246",
        "10",
        "251",
        "137",
        "21",
        "50",
        "67",
        "101",
        "128",
        "152",
        "169",
        "175",
        "218",
        "231",
        "237",
        "304",
        "312",
        "319",
        "323",
        "55"
      ],
      "publicConsultation": "",
      "documents": [
        {
          "textUrl": "https://www.cdep.ro/proiecte/bp/2025/100/60/7/in167.pdf",
          "title": "Adresa iniţiatorului"
        },
        {
          "textUrl": "https://www.cdep.ro/proiecte/bp/2025/100/60/7/em167.pdf",
          "title": "Expunerea de motive"
        },
        {
          "textUrl": "https://www.cdep.ro/proiecte/bp/2025/100/60/7/pl167.pdf",
          "title": "Forma iniţiatorului"
        }
      ],
      "url": "https://www.cdep.ro//pls/proiecte/upl_pck2015.proiect?idp=22365"
    },
    {
      "idp": "22391",
      "title": "Propunere legislativă pentru modificarea Legii nr.115/2015 pentru alegerea autorităţilor administraţiei publice locale, pentru modificarea Legii administraţiei publice locale nr.215/2001, precum şi pentru modificarea şi completarea Legii nr.393/2004 privind Statutul aleşilor localiDerularea procedurii legislative",
      "registrationNumber": {
        "bpi": "198/02-06-2025",
        "deputyChamber": "BP198/02.06.2025"
      },
      "legislativeProcedure": "cf. Constitutiei revizuita în 2003",
      "decidingChamber": "Camera Deputaţilor",
      "type": "Propunere legislativa\npentru\nmodificarea\nL. nr.\n215/2001\nmodificarea\nL. nr.\n393/2004\nmodificarea\nL. nr.\n115/2015",
      "emergencyProcedure": false,
      "status": {
        "short": "la senat",
        "long": "la Senat"
      },
      "initiators": [
        "3",
        "62",
        "86",
        "103",
        "135",
        "245",
        "246",
        "280",
        "318",
        "158",
        "251",
        "21",
        "50",
        "67",
        "75",
        "101",
        "128",
        "152",
        "148",
        "169",
        "175",
        "218",
        "231",
        "237",
        "304",
        "312",
        "319",
        "323"
      ],
      "publicConsultation": "",
      "documents": [
        {
          "textUrl": "https://www.cdep.ro/proiecte/bp/2025/100/90/8/in198.pdf",
          "title": "Adresa iniţiatorului"
        },
        {
          "textUrl": "https://www.cdep.ro/proiecte/bp/2025/100/90/8/em198.pdf",
          "title": "Expunerea de motive"
        },
        {
          "textUrl": "https://www.cdep.ro/proiecte/bp/2025/100/90/8/pl198.pdf",
          "title": "Forma iniţiatorului"
        }
      ],
      "url": "https://www.cdep.ro//pls/proiecte/upl_pck2015.proiect?idp=22391"
    },
    {
      "idp": "22460",
      "title": "Propunere legislativă pentru completarea Legii nr.208/2015 privind alegerea Senatului şi a Camerei Deputaţilor, precum şi pentru organizarea şi funcţionarea Autorităţii Electorale Permanente şi pentru modificarea şi completarea Legii nr.96/2006 privind statutul deputaţilor şi al senatorilorDerularea procedurii legislative",
      "registrationNumber": {
        "bpi": "242/18-06-2025",
        "deputyChamber": "BP242/18.06.2025"
      },
      "legislativeProcedure": "cf. Constitutiei revizuita în 2003",
      "decidingChamber": "Camera Deputaţilor",
      "type": "Propunere legislativa\npentru\nmodificarea\nL. nr.\n208/2015",
      "emergencyProcedure": false,
      "status": {
        "short": "",
        "long": ""
      },
      "initiators": [
        "318",
        "21",
        "101",
        "128",
        "152",
        "169",
        "175",
        "231",
        "237",
        "304",
        "312",
        "319",
        "323",
        "52",
        "132",
        "229",
        "257"
      ],
      "publicConsultation": "",
      "documents": [
        {
          "textUrl": "https://www.cdep.ro/proiecte/bp/2025/200/40/2/in242.pdf",
          "title": "Adresa iniţiatorului"
        },
        {
          "textUrl": "https://www.cdep.ro/proiecte/bp/2025/200/40/2/em242.pdf",
          "title": "Expunerea de motive"
        },
        {
          "textUrl": "https://www.cdep.ro/proiecte/bp/2025/200/40/2/pl242.pdf",
          "title": "Forma iniţiatorului"
        }
      ],
      "url": "https://www.cdep.ro//pls/proiecte/upl_pck2015.proiect?idp=22460"
    },
    {
      "idp": "22382",
      "title": "Propunere legislativă pentru modificarea art.77 alin.(10) din Legea nr.227/2015 privind Codul fiscalDerularea procedurii legislative",
      "registrationNumber": {
        "bpi": "188/28-05-2025",
        "deputyChamber": "BP188/28.05.2025"
      },
      "legislativeProcedure": "cf. Constitutiei revizuita în 2003",
      "decidingChamber": "Camera Deputaţilor",
      "type": "Propunere legislativa\npentru\nmodificarea\nL. nr.\n227/2015",
      "emergencyProcedure": false,
      "status": {
        "short": "la senat",
        "long": "la Senat"
      },
      "initiators": [
        "3",
        "62",
        "86",
        "103",
        "135",
        "245",
        "246",
        "280",
        "318",
        "158",
        "21",
        "50",
        "67",
        "75",
        "101",
        "128",
        "152",
        "148",
        "169",
        "175",
        "218",
        "231",
        "237",
        "304",
        "312",
        "319",
        "323",
        "52",
        "55",
        "257"
      ],
      "publicConsultation": "",
      "documents": [
        {
          "textUrl": "https://www.cdep.ro/proiecte/bp/2025/100/80/8/in188.pdf",
          "title": "Adresa iniţiatorului"
        },
        {
          "textUrl": "https://www.cdep.ro/proiecte/bp/2025/100/80/8/em188.pdf",
          "title": "Expunerea de motive"
        },
        {
          "textUrl": "https://www.cdep.ro/proiecte/bp/2025/100/80/8/pl188.pdf",
          "title": "Forma iniţiatorului"
        }
      ],
      "url": "https://www.cdep.ro//pls/proiecte/upl_pck2015.proiect?idp=22382"
    }
  ]
}
