{
  "version": "0.0.3",
  "lastUpdated": "2025-07-17T00:24:19.920Z",
  "data": {
    "idm": "322",
    "name": "Silviu VEXLER",
    "url": "https://www.cdep.ro/pls/parlam/structura2015.mp?idm=322&cam=2",
    "photoUrl": "https://www.cdep.ro/parlamentari/l2024/VexlerSilviu.JPG",
    "group": {
      "idg": "8",
      "name": "Grupul parlamentar al minorităţilor naţionale",
      "url": "https://www.cdep.ro/pls/parlam/structura2015.gp?idg=8"
    },
    "activity": {
      "Luări de cuvânt": {
        "count": 10,
        "url": "https://www.cdep.ro/pls/steno/steno2015.lista?idv=6741&leg=2024&idl=1"
      },
      "Propuneri legislative iniţiate": {
        "count": 7,
        "url": "https://www.cdep.ro/pls/parlam/structura2015.mp?idm=322&cam=2&leg=2024&pag=2&idl=1&prn=0&par="
      },
      "Întrebari şi interpelări": {
        "count": 2,
        "url": "https://www.cdep.ro/pls/parlam/structura2015.mp?idm=322&cam=2&leg=2024&pag=3&idl=1&prn=0&par="
      }
    }
  }
}