{
  "version": "0.0.1",
  "lastUpdated": "2025-09-26T00:05:59.280Z",
  "data": [
    {
      "ids": "8914",
      "idv": "7328",
      "idm": "298",
      "date": "2025-07-14T00:00:00.000Z",
      "title": "Sedinta comuna a Camerei Deputatilor si Senatului din 14 iulie      2025 (sesiune extraordinara)",
      "link": "https://www.cdep.ro/pls/steno/steno2015.sumar?ids=8914&idl=1",
      "transcripts": [
        {
          "fullTextUrl": "https://www.cdep.ro/pls/steno/steno2015.stenograma?ids=8914&idm=3&idl=1",
          "relevantSectionUrl": "https://www.cdep.ro/pls/steno/steno2015.stenograma?ids=8914&idm=3&sir=&sep=and&idv=7328&idl=1&nav=%3Ca%20href=%22/pls/steno/steno2015.cautare%3Fcam=%26com=0%26leg=%26topic1=0%26topic2=0%26topic3=0%26topic4=0%26topic5=0%26nrp=%26anp=%26idv=7328%26sir=%26sep=and%26ts=0%26dat1=20-12-2024%26dat2=22-09-2025%26ord=0%26pag=1000%26idl=1%22%3EInterogare%3C/a%3E%20%26gt%20%3Ca%20href=%22/pls/steno/steno2015.lista%3Fcam=%26com=0%26leg=%26topic1=0%26topic2=0%26topic3=0%26topic4=0%26topic5=0%26nrp=%26anp=%26idv=7328%26sir=%26sep=and%26ts=0%26dat1=20-12-2024%26dat2=22-09-2025%26ord=0%26pag=1000%26idl=1%26pags=1%22%3ERezultate%3C/a%3E",
          "description": "Vacantarea unei funcţii de membru al Colegiului director al Consiliului Naţional pentru Combaterea Discriminării, ca urmare a demisiei. Dezbaterea Proiectului de Hotărâre a Parlamentului privind vacantarea unei funcţii de membru al Colegiului director al Consiliului Naţional pentru Combaterea Discriminării, ca urmare a demisiei (adoptat)."
        }
      ]
    },
    {
      "ids": "8908",
      "idv": "7328",
      "idm": "298",
      "date": "2025-06-24T00:00:00.000Z",
      "title": "Sedinta Camerei Deputatilor din 24 iunie      2025",
      "link": "https://www.cdep.ro/pls/steno/steno2015.sumar?ids=8908&idl=1",
      "transcripts": [
        {
          "fullTextUrl": "https://www.cdep.ro/pls/steno/steno2015.stenograma?ids=8908&idm=10&idl=1",
          "relevantSectionUrl": "https://www.cdep.ro/pls/steno/steno2015.stenograma?ids=8908&idm=10&sir=&sep=and&idv=7328&idl=1&nav=%3Ca%20href=%22/pls/steno/steno2015.cautare%3Fcam=%26com=0%26leg=%26topic1=0%26topic2=0%26topic3=0%26topic4=0%26topic5=0%26nrp=%26anp=%26idv=7328%26sir=%26sep=and%26ts=0%26dat1=20-12-2024%26dat2=22-09-2025%26ord=0%26pag=1000%26idl=1%22%3EInterogare%3C/a%3E%20%26gt%20%3Ca%20href=%22/pls/steno/steno2015.lista%3Fcam=%26com=0%26leg=%26topic1=0%26topic2=0%26topic3=0%26topic4=0%26topic5=0%26nrp=%26anp=%26idv=7328%26sir=%26sep=and%26ts=0%26dat1=20-12-2024%26dat2=22-09-2025%26ord=0%26pag=1000%26idl=1%26pags=1%22%3ERezultate%3C/a%3E",
          "description": "Numirea unui judecător la Curtea Constituţională (vot secret cu buletine de vot)."
        }
      ]
    },
    {
      "ids": "8905",
      "idv": "7328",
      "idm": "298",
      "date": "2025-06-18T00:00:00.000Z",
      "title": "Sedinta Camerei Deputatilor din 18 iunie      2025",
      "link": "https://www.cdep.ro/pls/steno/steno2015.sumar?ids=8905&idl=1",
      "transcripts": [
        {
          "fullTextUrl": "https://www.cdep.ro/pls/steno/steno2015.stenograma?ids=8905&idm=8&idl=1",
          "relevantSectionUrl": "https://www.cdep.ro/pls/steno/steno2015.stenograma?ids=8905&idm=8&sir=&sep=and&idv=7328&idl=1&nav=%3Ca%20href=%22/pls/steno/steno2015.cautare%3Fcam=%26com=0%26leg=%26topic1=0%26topic2=0%26topic3=0%26topic4=0%26topic5=0%26nrp=%26anp=%26idv=7328%26sir=%26sep=and%26ts=0%26dat1=20-12-2024%26dat2=22-09-2025%26ord=0%26pag=1000%26idl=1%22%3EInterogare%3C/a%3E%20%26gt%20%3Ca%20href=%22/pls/steno/steno2015.lista%3Fcam=%26com=0%26leg=%26topic1=0%26topic2=0%26topic3=0%26topic4=0%26topic5=0%26nrp=%26anp=%26idv=7328%26sir=%26sep=and%26ts=0%26dat1=20-12-2024%26dat2=22-09-2025%26ord=0%26pag=1000%26idl=1%26pags=1%22%3ERezultate%3C/a%3E",
          "description": "Dezbaterea Proiectului de Lege pentru aprobarea Ordonanţei de urgenţă a Guvernului nr. 105/2024 privind unele măsuri de protecţie socială (PL-x 497/2024) (rămas pentru votul final)."
        }
      ]
    },
    {
      "ids": "8903",
      "idv": "7328",
      "idm": "298",
      "date": "2025-06-11T00:00:00.000Z",
      "title": "Sedinta Camerei Deputatilor din 11 iunie      2025",
      "link": "https://www.cdep.ro/pls/steno/steno2015.sumar?ids=8903&idl=1",
      "transcripts": [
        {
          "fullTextUrl": "https://www.cdep.ro/pls/steno/steno2015.stenograma?ids=8903&idm=7&idl=1",
          "relevantSectionUrl": "https://www.cdep.ro/pls/steno/steno2015.stenograma?ids=8903&idm=7&sir=&sep=and&idv=7328&idl=1&nav=%3Ca%20href=%22/pls/steno/steno2015.cautare%3Fcam=%26com=0%26leg=%26topic1=0%26topic2=0%26topic3=0%26topic4=0%26topic5=0%26nrp=%26anp=%26idv=7328%26sir=%26sep=and%26ts=0%26dat1=20-12-2024%26dat2=22-09-2025%26ord=0%26pag=1000%26idl=1%22%3EInterogare%3C/a%3E%20%26gt%20%3Ca%20href=%22/pls/steno/steno2015.lista%3Fcam=%26com=0%26leg=%26topic1=0%26topic2=0%26topic3=0%26topic4=0%26topic5=0%26nrp=%26anp=%26idv=7328%26sir=%26sep=and%26ts=0%26dat1=20-12-2024%26dat2=22-09-2025%26ord=0%26pag=1000%26idl=1%26pags=1%22%3ERezultate%3C/a%3E",
          "description": "Dezbaterea Proiectului de Lege privind unele măsuri pentru prevenirea şi combaterea antisemitismului, xenofobiei, radicalizării şi a discursului instigator la ură (PL-x 168/2025) (rămas pentru votul final)."
        },
        {
          "fullTextUrl": "https://www.cdep.ro/pls/steno/steno2015.stenograma?ids=8903&idm=8&idl=1",
          "relevantSectionUrl": "https://www.cdep.ro/pls/steno/steno2015.stenograma?ids=8903&idm=8&sir=&sep=and&idv=7328&idl=1&nav=%3Ca%20href=%22/pls/steno/steno2015.cautare%3Fcam=%26com=0%26leg=%26topic1=0%26topic2=0%26topic3=0%26topic4=0%26topic5=0%26nrp=%26anp=%26idv=7328%26sir=%26sep=and%26ts=0%26dat1=20-12-2024%26dat2=22-09-2025%26ord=0%26pag=1000%26idl=1%22%3EInterogare%3C/a%3E%20%26gt%20%3Ca%20href=%22/pls/steno/steno2015.lista%3Fcam=%26com=0%26leg=%26topic1=0%26topic2=0%26topic3=0%26topic4=0%26topic5=0%26nrp=%26anp=%26idv=7328%26sir=%26sep=and%26ts=0%26dat1=20-12-2024%26dat2=22-09-2025%26ord=0%26pag=1000%26idl=1%26pags=1%22%3ERezultate%3C/a%3E",
          "description": "Supunerea la votul final a:"
        },
        {
          "fullTextUrl": "https://www.cdep.ro/pls/steno/steno2015.stenograma?ids=8903&idm=8,007&idl=1",
          "relevantSectionUrl": "https://www.cdep.ro/pls/steno/steno2015.stenograma?ids=8903&idm=8,007&sir=&sep=and&idv=7328&idl=1&nav=%3Ca%20href=%22/pls/steno/steno2015.cautare%3Fcam=%26com=0%26leg=%26topic1=0%26topic2=0%26topic3=0%26topic4=0%26topic5=0%26nrp=%26anp=%26idv=7328%26sir=%26sep=and%26ts=0%26dat1=20-12-2024%26dat2=22-09-2025%26ord=0%26pag=1000%26idl=1%22%3EInterogare%3C/a%3E%20%26gt%20%3Ca%20href=%22/pls/steno/steno2015.lista%3Fcam=%26com=0%26leg=%26topic1=0%26topic2=0%26topic3=0%26topic4=0%26topic5=0%26nrp=%26anp=%26idv=7328%26sir=%26sep=and%26ts=0%26dat1=20-12-2024%26dat2=22-09-2025%26ord=0%26pag=1000%26idl=1%26pags=1%22%3ERezultate%3C/a%3E",
          "description": "Proiectului de Lege privind aprobarea Ordonanţei de urgenţă a Guvernului nr. 68/2024 pentru modificarea şi completarea Ordonanţei de urgenţă a Guvernului nr. 166/2022 privind unele măsuri pentru acordarea unui sprijin categoriilor de persoane vulnerabile pentru compensarea preţului la energie, suportat parţial din fonduri externe nerambursabile (PL-x 456/2024) (adoptat);"
        },
        {
          "fullTextUrl": "https://www.cdep.ro/pls/steno/steno2015.stenograma?ids=8903&idm=8,008&idl=1",
          "relevantSectionUrl": "https://www.cdep.ro/pls/steno/steno2015.stenograma?ids=8903&idm=8,008&sir=&sep=and&idv=7328&idl=1&nav=%3Ca%20href=%22/pls/steno/steno2015.cautare%3Fcam=%26com=0%26leg=%26topic1=0%26topic2=0%26topic3=0%26topic4=0%26topic5=0%26nrp=%26anp=%26idv=7328%26sir=%26sep=and%26ts=0%26dat1=20-12-2024%26dat2=22-09-2025%26ord=0%26pag=1000%26idl=1%22%3EInterogare%3C/a%3E%20%26gt%20%3Ca%20href=%22/pls/steno/steno2015.lista%3Fcam=%26com=0%26leg=%26topic1=0%26topic2=0%26topic3=0%26topic4=0%26topic5=0%26nrp=%26anp=%26idv=7328%26sir=%26sep=and%26ts=0%26dat1=20-12-2024%26dat2=22-09-2025%26ord=0%26pag=1000%26idl=1%26pags=1%22%3ERezultate%3C/a%3E",
          "description": "Proiectului de Lege privind aprobarea Ordonanţei de urgenţă a Guvernului nr. 59/2019 pentru modificarea art. 35 din Legea nr. 269/2003 privind Statutul Corpului diplomatic şi consular al României (PL-x 429/2019) (adoptat);"
        }
      ]
    },
    {
      "ids": "8900",
      "idv": "7328",
      "idm": "298",
      "date": "2025-06-04T00:00:00.000Z",
      "title": "Sedinta Camerei Deputatilor din 4 iunie      2025",
      "link": "https://www.cdep.ro/pls/steno/steno2015.sumar?ids=8900&idl=1",
      "transcripts": [
        {
          "fullTextUrl": "https://www.cdep.ro/pls/steno/steno2015.stenograma?ids=8900&idm=4&idl=1",
          "relevantSectionUrl": "https://www.cdep.ro/pls/steno/steno2015.stenograma?ids=8900&idm=4&sir=&sep=and&idv=7328&idl=1&nav=%3Ca%20href=%22/pls/steno/steno2015.cautare%3Fcam=%26com=0%26leg=%26topic1=0%26topic2=0%26topic3=0%26topic4=0%26topic5=0%26nrp=%26anp=%26idv=7328%26sir=%26sep=and%26ts=0%26dat1=20-12-2024%26dat2=22-09-2025%26ord=0%26pag=1000%26idl=1%22%3EInterogare%3C/a%3E%20%26gt%20%3Ca%20href=%22/pls/steno/steno2015.lista%3Fcam=%26com=0%26leg=%26topic1=0%26topic2=0%26topic3=0%26topic4=0%26topic5=0%26nrp=%26anp=%26idv=7328%26sir=%26sep=and%26ts=0%26dat1=20-12-2024%26dat2=22-09-2025%26ord=0%26pag=1000%26idl=1%26pags=1%22%3ERezultate%3C/a%3E",
          "description": "Intervenţii din partea grupurilor parlamentare pentru marcarea Zilei Tratatului de la Trianon."
        }
      ]
    },
    {
      "ids": "8898",
      "idv": "7328",
      "idm": "298",
      "date": "2025-05-28T00:00:00.000Z",
      "title": "Sedinta Camerei Deputatilor din 28 mai        2025",
      "link": "https://www.cdep.ro/pls/steno/steno2015.sumar?ids=8898&idl=1",
      "transcripts": [
        {
          "fullTextUrl": "https://www.cdep.ro/pls/steno/steno2015.stenograma?ids=8898&idm=4&idl=1",
          "relevantSectionUrl": "https://www.cdep.ro/pls/steno/steno2015.stenograma?ids=8898&idm=4&sir=&sep=and&idv=7328&idl=1&nav=%3Ca%20href=%22/pls/steno/steno2015.cautare%3Fcam=%26com=0%26leg=%26topic1=0%26topic2=0%26topic3=0%26topic4=0%26topic5=0%26nrp=%26anp=%26idv=7328%26sir=%26sep=and%26ts=0%26dat1=20-12-2024%26dat2=22-09-2025%26ord=0%26pag=1000%26idl=1%22%3EInterogare%3C/a%3E%20%26gt%20%3Ca%20href=%22/pls/steno/steno2015.lista%3Fcam=%26com=0%26leg=%26topic1=0%26topic2=0%26topic3=0%26topic4=0%26topic5=0%26nrp=%26anp=%26idv=7328%26sir=%26sep=and%26ts=0%26dat1=20-12-2024%26dat2=22-09-2025%26ord=0%26pag=1000%26idl=1%26pags=1%22%3ERezultate%3C/a%3E",
          "description": "Dezbaterea Proiectului de Lege privind aprobarea Ordonanţei Guvernului nr. 8/2025 pentru modificarea şi completarea Legii nr. 152/1998 privind înfiinţarea Agenţiei Naţionale pentru Locuinţe (PL-x 75/2025) (rămas pentru votul final)."
        }
      ]
    },
    {
      "ids": "8897",
      "idv": "7328",
      "idm": "298",
      "date": "2025-05-26T00:00:00.000Z",
      "title": "Sedinta Camerei Deputatilor din 26 mai        2025",
      "link": "https://www.cdep.ro/pls/steno/steno2015.sumar?ids=8897&idl=1",
      "transcripts": [
        {
          "fullTextUrl": "https://www.cdep.ro/pls/steno/steno2015.stenograma?ids=8897&idm=3&idl=1",
          "relevantSectionUrl": "https://www.cdep.ro/pls/steno/steno2015.stenograma?ids=8897&idm=3&sir=&sep=and&idv=7328&idl=1&nav=%3Ca%20href=%22/pls/steno/steno2015.cautare%3Fcam=%26com=0%26leg=%26topic1=0%26topic2=0%26topic3=0%26topic4=0%26topic5=0%26nrp=%26anp=%26idv=7328%26sir=%26sep=and%26ts=0%26dat1=20-12-2024%26dat2=22-09-2025%26ord=0%26pag=1000%26idl=1%22%3EInterogare%3C/a%3E%20%26gt%20%3Ca%20href=%22/pls/steno/steno2015.lista%3Fcam=%26com=0%26leg=%26topic1=0%26topic2=0%26topic3=0%26topic4=0%26topic5=0%26nrp=%26anp=%26idv=7328%26sir=%26sep=and%26ts=0%26dat1=20-12-2024%26dat2=22-09-2025%26ord=0%26pag=1000%26idl=1%26pags=1%22%3ERezultate%3C/a%3E",
          "description": "Aprobarea unor modificări ale ordinii de zi."
        }
      ]
    },
    {
      "ids": "8892",
      "idv": "7328",
      "idm": "298",
      "date": "2025-05-13T00:00:00.000Z",
      "title": "Sedinta Camerei Deputatilor din 13 mai        2025",
      "link": "https://www.cdep.ro/pls/steno/steno2015.sumar?ids=8892&idl=1",
      "transcripts": [
        {
          "fullTextUrl": "https://www.cdep.ro/pls/steno/steno2015.stenograma?ids=8892&idm=5&idl=1",
          "relevantSectionUrl": "https://www.cdep.ro/pls/steno/steno2015.stenograma?ids=8892&idm=5&sir=&sep=and&idv=7328&idl=1&nav=%3Ca%20href=%22/pls/steno/steno2015.cautare%3Fcam=%26com=0%26leg=%26topic1=0%26topic2=0%26topic3=0%26topic4=0%26topic5=0%26nrp=%26anp=%26idv=7328%26sir=%26sep=and%26ts=0%26dat1=20-12-2024%26dat2=22-09-2025%26ord=0%26pag=1000%26idl=1%22%3EInterogare%3C/a%3E%20%26gt%20%3Ca%20href=%22/pls/steno/steno2015.lista%3Fcam=%26com=0%26leg=%26topic1=0%26topic2=0%26topic3=0%26topic4=0%26topic5=0%26nrp=%26anp=%26idv=7328%26sir=%26sep=and%26ts=0%26dat1=20-12-2024%26dat2=22-09-2025%26ord=0%26pag=1000%26idl=1%26pags=1%22%3ERezultate%3C/a%3E",
          "description": "Dezbaterea Proiectului de Lege privind aprobarea Ordonanţei de urgenţă a Guvernului nr. 145/2024 pentru modificarea art. 16 alin. (1) din Legea nr. 195/2018 privind aprobarea Programului de susţinere a crescătorilor de suine pentru activitatea de reproducţie, precum şi a art. 15 alin. (1) din Legea nr. 227/2018 privind aprobarea Programului de susţinere pentru activitatea de reproducţie, incubaţie şi de creştere în sectorul avicol (PL-x 46/2025) (rămas pentru votul final)."
        },
        {
          "fullTextUrl": "https://www.cdep.ro/pls/steno/steno2015.stenograma?ids=8892&idm=2&idl=1",
          "relevantSectionUrl": "https://www.cdep.ro/pls/steno/steno2015.stenograma?ids=8892&idm=2&sir=&sep=and&idv=7328&idl=1&nav=%3Ca%20href=%22/pls/steno/steno2015.cautare%3Fcam=%26com=0%26leg=%26topic1=0%26topic2=0%26topic3=0%26topic4=0%26topic5=0%26nrp=%26anp=%26idv=7328%26sir=%26sep=and%26ts=0%26dat1=20-12-2024%26dat2=22-09-2025%26ord=0%26pag=1000%26idl=1%22%3EInterogare%3C/a%3E%20%26gt%20%3Ca%20href=%22/pls/steno/steno2015.lista%3Fcam=%26com=0%26leg=%26topic1=0%26topic2=0%26topic3=0%26topic4=0%26topic5=0%26nrp=%26anp=%26idv=7328%26sir=%26sep=and%26ts=0%26dat1=20-12-2024%26dat2=22-09-2025%26ord=0%26pag=1000%26idl=1%26pags=1%22%3ERezultate%3C/a%3E",
          "description": "Dezbaterea Proiectului de Lege pentru instituirea anului 2027 - Anul Ion I.C. Brătianu (PL-x 167/2024) (rămas pentru votul final)."
        }
      ]
    },
    {
      "ids": "8890",
      "idv": "7328",
      "idm": "298",
      "date": "2025-05-07T00:00:00.000Z",
      "title": "Sedinta Camerei Deputatilor din 7 mai        2025",
      "link": "https://www.cdep.ro/pls/steno/steno2015.sumar?ids=8890&idl=1",
      "transcripts": [
        {
          "fullTextUrl": "https://www.cdep.ro/pls/steno/steno2015.stenograma?ids=8890&idm=6&idl=1",
          "relevantSectionUrl": "https://www.cdep.ro/pls/steno/steno2015.stenograma?ids=8890&idm=6&sir=&sep=and&idv=7328&idl=1&nav=%3Ca%20href=%22/pls/steno/steno2015.cautare%3Fcam=%26com=0%26leg=%26topic1=0%26topic2=0%26topic3=0%26topic4=0%26topic5=0%26nrp=%26anp=%26idv=7328%26sir=%26sep=and%26ts=0%26dat1=20-12-2024%26dat2=22-09-2025%26ord=0%26pag=1000%26idl=1%22%3EInterogare%3C/a%3E%20%26gt%20%3Ca%20href=%22/pls/steno/steno2015.lista%3Fcam=%26com=0%26leg=%26topic1=0%26topic2=0%26topic3=0%26topic4=0%26topic5=0%26nrp=%26anp=%26idv=7328%26sir=%26sep=and%26ts=0%26dat1=20-12-2024%26dat2=22-09-2025%26ord=0%26pag=1000%26idl=1%26pags=1%22%3ERezultate%3C/a%3E",
          "description": "Dezbaterea Proiectului de Lege pentru aprobarea Ordonanţei de urgenţă a Guvernului nr. 67/2024 privind reorganizarea şi funcţionarea Institutului Naţional de Administraţie (PL-x 455/2024) (rămas pentru votul final)."
        }
      ]
    },
    {
      "ids": "8889",
      "idv": "7328",
      "idm": "298",
      "date": "2025-05-06T00:00:00.000Z",
      "title": "Sedinta Camerei Deputatilor din 6 mai        2025",
      "link": "https://www.cdep.ro/pls/steno/steno2015.sumar?ids=8889&idl=1",
      "transcripts": [
        {
          "fullTextUrl": "https://www.cdep.ro/pls/steno/steno2015.stenograma?ids=8889&idm=2&idl=1",
          "relevantSectionUrl": "https://www.cdep.ro/pls/steno/steno2015.stenograma?ids=8889&idm=2&sir=&sep=and&idv=7328&idl=1&nav=%3Ca%20href=%22/pls/steno/steno2015.cautare%3Fcam=%26com=0%26leg=%26topic1=0%26topic2=0%26topic3=0%26topic4=0%26topic5=0%26nrp=%26anp=%26idv=7328%26sir=%26sep=and%26ts=0%26dat1=20-12-2024%26dat2=22-09-2025%26ord=0%26pag=1000%26idl=1%22%3EInterogare%3C/a%3E%20%26gt%20%3Ca%20href=%22/pls/steno/steno2015.lista%3Fcam=%26com=0%26leg=%26topic1=0%26topic2=0%26topic3=0%26topic4=0%26topic5=0%26nrp=%26anp=%26idv=7328%26sir=%26sep=and%26ts=0%26dat1=20-12-2024%26dat2=22-09-2025%26ord=0%26pag=1000%26idl=1%26pags=1%22%3ERezultate%3C/a%3E",
          "description": "Informare privind demisia domnului deputat Dorin Popa din Grupul parlamentar POT şi activarea sa ca deputat neafiliat."
        },
        {
          "fullTextUrl": "https://www.cdep.ro/pls/steno/steno2015.stenograma?ids=8889&idm=4&idl=1",
          "relevantSectionUrl": "https://www.cdep.ro/pls/steno/steno2015.stenograma?ids=8889&idm=4&sir=&sep=and&idv=7328&idl=1&nav=%3Ca%20href=%22/pls/steno/steno2015.cautare%3Fcam=%26com=0%26leg=%26topic1=0%26topic2=0%26topic3=0%26topic4=0%26topic5=0%26nrp=%26anp=%26idv=7328%26sir=%26sep=and%26ts=0%26dat1=20-12-2024%26dat2=22-09-2025%26ord=0%26pag=1000%26idl=1%22%3EInterogare%3C/a%3E%20%26gt%20%3Ca%20href=%22/pls/steno/steno2015.lista%3Fcam=%26com=0%26leg=%26topic1=0%26topic2=0%26topic3=0%26topic4=0%26topic5=0%26nrp=%26anp=%26idv=7328%26sir=%26sep=and%26ts=0%26dat1=20-12-2024%26dat2=22-09-2025%26ord=0%26pag=1000%26idl=1%26pags=1%22%3ERezultate%3C/a%3E",
          "description": "Dezbaterea Proiectului de Lege pentru modificarea art. 11 din Legea nr. 122/2006 privind azilul în România (PL-x 712/2022) (rămas pentru votul final)."
        }
      ]
    },
    {
      "ids": "8888",
      "idv": "7328",
      "idm": "298",
      "date": "2025-04-23T00:00:00.000Z",
      "title": "Sedinta Camerei Deputatilor din 23 aprilie    2025",
      "link": "https://www.cdep.ro/pls/steno/steno2015.sumar?ids=8888&idl=1",
      "transcripts": [
        {
          "fullTextUrl": "https://www.cdep.ro/pls/steno/steno2015.stenograma?ids=8888&idm=13&idl=1",
          "relevantSectionUrl": "https://www.cdep.ro/pls/steno/steno2015.stenograma?ids=8888&idm=13&sir=&sep=and&idv=7328&idl=1&nav=%3Ca%20href=%22/pls/steno/steno2015.cautare%3Fcam=%26com=0%26leg=%26topic1=0%26topic2=0%26topic3=0%26topic4=0%26topic5=0%26nrp=%26anp=%26idv=7328%26sir=%26sep=and%26ts=0%26dat1=20-12-2024%26dat2=22-09-2025%26ord=0%26pag=1000%26idl=1%22%3EInterogare%3C/a%3E%20%26gt%20%3Ca%20href=%22/pls/steno/steno2015.lista%3Fcam=%26com=0%26leg=%26topic1=0%26topic2=0%26topic3=0%26topic4=0%26topic5=0%26nrp=%26anp=%26idv=7328%26sir=%26sep=and%26ts=0%26dat1=20-12-2024%26dat2=22-09-2025%26ord=0%26pag=1000%26idl=1%26pags=1%22%3ERezultate%3C/a%3E",
          "description": "Supunerea la votul final a:"
        },
        {
          "fullTextUrl": "https://www.cdep.ro/pls/steno/steno2015.stenograma?ids=8888&idm=13,01&idl=1",
          "relevantSectionUrl": "https://www.cdep.ro/pls/steno/steno2015.stenograma?ids=8888&idm=13,01&sir=&sep=and&idv=7328&idl=1&nav=%3Ca%20href=%22/pls/steno/steno2015.cautare%3Fcam=%26com=0%26leg=%26topic1=0%26topic2=0%26topic3=0%26topic4=0%26topic5=0%26nrp=%26anp=%26idv=7328%26sir=%26sep=and%26ts=0%26dat1=20-12-2024%26dat2=22-09-2025%26ord=0%26pag=1000%26idl=1%22%3EInterogare%3C/a%3E%20%26gt%20%3Ca%20href=%22/pls/steno/steno2015.lista%3Fcam=%26com=0%26leg=%26topic1=0%26topic2=0%26topic3=0%26topic4=0%26topic5=0%26nrp=%26anp=%26idv=7328%26sir=%26sep=and%26ts=0%26dat1=20-12-2024%26dat2=22-09-2025%26ord=0%26pag=1000%26idl=1%26pags=1%22%3ERezultate%3C/a%3E",
          "description": "Propunerii legislative privind modificarea unor acte normative din domeniul pensiilor de serviciu (Pl-x 103/2025) (adoptată)."
        }
      ]
    },
    {
      "ids": "8884",
      "idv": "7328",
      "idm": "298",
      "date": "2025-04-08T00:00:00.000Z",
      "title": "Sedinta Camerei Deputatilor din 8 aprilie    2025",
      "link": "https://www.cdep.ro/pls/steno/steno2015.sumar?ids=8884&idl=1",
      "transcripts": [
        {
          "fullTextUrl": "https://www.cdep.ro/pls/steno/steno2015.stenograma?ids=8884&idm=4&idl=1",
          "relevantSectionUrl": "https://www.cdep.ro/pls/steno/steno2015.stenograma?ids=8884&idm=4&sir=&sep=and&idv=7328&idl=1&nav=%3Ca%20href=%22/pls/steno/steno2015.cautare%3Fcam=%26com=0%26leg=%26topic1=0%26topic2=0%26topic3=0%26topic4=0%26topic5=0%26nrp=%26anp=%26idv=7328%26sir=%26sep=and%26ts=0%26dat1=20-12-2024%26dat2=22-09-2025%26ord=0%26pag=1000%26idl=1%22%3EInterogare%3C/a%3E%20%26gt%20%3Ca%20href=%22/pls/steno/steno2015.lista%3Fcam=%26com=0%26leg=%26topic1=0%26topic2=0%26topic3=0%26topic4=0%26topic5=0%26nrp=%26anp=%26idv=7328%26sir=%26sep=and%26ts=0%26dat1=20-12-2024%26dat2=22-09-2025%26ord=0%26pag=1000%26idl=1%26pags=1%22%3ERezultate%3C/a%3E",
          "description": "Dezbaterea Proiectului de Lege pentru completarea Ordonanţei de urgenţă a Guvernului n. 28/2013 pentru aprobarea Programului naţional de dezvoltare locală (PL-x 629/2023) (rămas pentru votul final)."
        }
      ]
    },
    {
      "ids": "8881",
      "idv": "7328",
      "idm": "298",
      "date": "2025-04-02T00:00:00.000Z",
      "title": "Sedinta Camerei Deputatilor din 2 aprilie    2025",
      "link": "https://www.cdep.ro/pls/steno/steno2015.sumar?ids=8881&idl=1",
      "transcripts": [
        {
          "fullTextUrl": "https://www.cdep.ro/pls/steno/steno2015.stenograma?ids=8881&idm=3&idl=1",
          "relevantSectionUrl": "https://www.cdep.ro/pls/steno/steno2015.stenograma?ids=8881&idm=3&sir=&sep=and&idv=7328&idl=1&nav=%3Ca%20href=%22/pls/steno/steno2015.cautare%3Fcam=%26com=0%26leg=%26topic1=0%26topic2=0%26topic3=0%26topic4=0%26topic5=0%26nrp=%26anp=%26idv=7328%26sir=%26sep=and%26ts=0%26dat1=20-12-2024%26dat2=22-09-2025%26ord=0%26pag=1000%26idl=1%22%3EInterogare%3C/a%3E%20%26gt%20%3Ca%20href=%22/pls/steno/steno2015.lista%3Fcam=%26com=0%26leg=%26topic1=0%26topic2=0%26topic3=0%26topic4=0%26topic5=0%26nrp=%26anp=%26idv=7328%26sir=%26sep=and%26ts=0%26dat1=20-12-2024%26dat2=22-09-2025%26ord=0%26pag=1000%26idl=1%26pags=1%22%3ERezultate%3C/a%3E",
          "description": "Prezentarea şi dezbaterea moţiunii simple intitulate \"De la democraţie la regim hibrid: România sub jugul poliţiei politice asmuţite de ministrul Predoiu\", iniţiată de 56 de deputaţi (MS 1/2025)."
        }
      ]
    },
    {
      "ids": "8880",
      "idv": "7328",
      "idm": "298",
      "date": "2025-03-31T00:00:00.000Z",
      "title": "Sedinta Camerei Deputatilor din 31 martie     2025",
      "link": "https://www.cdep.ro/pls/steno/steno2015.sumar?ids=8880&idl=1",
      "transcripts": [
        {
          "fullTextUrl": "https://www.cdep.ro/pls/steno/steno2015.stenograma?ids=8880&idm=13&idl=1",
          "relevantSectionUrl": "https://www.cdep.ro/pls/steno/steno2015.stenograma?ids=8880&idm=13&sir=&sep=and&idv=7328&idl=1&nav=%3Ca%20href=%22/pls/steno/steno2015.cautare%3Fcam=%26com=0%26leg=%26topic1=0%26topic2=0%26topic3=0%26topic4=0%26topic5=0%26nrp=%26anp=%26idv=7328%26sir=%26sep=and%26ts=0%26dat1=20-12-2024%26dat2=22-09-2025%26ord=0%26pag=1000%26idl=1%22%3EInterogare%3C/a%3E%20%26gt%20%3Ca%20href=%22/pls/steno/steno2015.lista%3Fcam=%26com=0%26leg=%26topic1=0%26topic2=0%26topic3=0%26topic4=0%26topic5=0%26nrp=%26anp=%26idv=7328%26sir=%26sep=and%26ts=0%26dat1=20-12-2024%26dat2=22-09-2025%26ord=0%26pag=1000%26idl=1%26pags=1%22%3ERezultate%3C/a%3E",
          "description": "Dezbaterea Propunerii legislative pentru completarea şi modificarea Legii privind organizarea şi funcţionarea statisticii oficiale în România nr. 226/2009 (Pl-x 567/2022) (rămasă pentru votul final)."
        }
      ]
    },
    {
      "ids": "8877",
      "idv": "7328",
      "idm": "298",
      "date": "2025-03-26T00:00:00.000Z",
      "title": "Sedinta Camerei Deputatilor din 26 martie     2025",
      "link": "https://www.cdep.ro/pls/steno/steno2015.sumar?ids=8877&idl=1",
      "transcripts": [
        {
          "fullTextUrl": "https://www.cdep.ro/pls/steno/steno2015.stenograma?ids=8877&idm=5&idl=1",
          "relevantSectionUrl": "https://www.cdep.ro/pls/steno/steno2015.stenograma?ids=8877&idm=5&sir=&sep=and&idv=7328&idl=1&nav=%3Ca%20href=%22/pls/steno/steno2015.cautare%3Fcam=%26com=0%26leg=%26topic1=0%26topic2=0%26topic3=0%26topic4=0%26topic5=0%26nrp=%26anp=%26idv=7328%26sir=%26sep=and%26ts=0%26dat1=20-12-2024%26dat2=22-09-2025%26ord=0%26pag=1000%26idl=1%22%3EInterogare%3C/a%3E%20%26gt%20%3Ca%20href=%22/pls/steno/steno2015.lista%3Fcam=%26com=0%26leg=%26topic1=0%26topic2=0%26topic3=0%26topic4=0%26topic5=0%26nrp=%26anp=%26idv=7328%26sir=%26sep=and%26ts=0%26dat1=20-12-2024%26dat2=22-09-2025%26ord=0%26pag=1000%26idl=1%26pags=1%22%3ERezultate%3C/a%3E",
          "description": "Informare privind depunerea moţiunii simple intitulate \"De la democraţie la regim hibrid: România sub jugul poliţiei politice asmuţite de ministrul Predoiu\", iniţiată de 56 de deputaţi."
        },
        {
          "fullTextUrl": "https://www.cdep.ro/pls/steno/steno2015.stenograma?ids=8877&idm=4&idl=1",
          "relevantSectionUrl": "https://www.cdep.ro/pls/steno/steno2015.stenograma?ids=8877&idm=4&sir=&sep=and&idv=7328&idl=1&nav=%3Ca%20href=%22/pls/steno/steno2015.cautare%3Fcam=%26com=0%26leg=%26topic1=0%26topic2=0%26topic3=0%26topic4=0%26topic5=0%26nrp=%26anp=%26idv=7328%26sir=%26sep=and%26ts=0%26dat1=20-12-2024%26dat2=22-09-2025%26ord=0%26pag=1000%26idl=1%22%3EInterogare%3C/a%3E%20%26gt%20%3Ca%20href=%22/pls/steno/steno2015.lista%3Fcam=%26com=0%26leg=%26topic1=0%26topic2=0%26topic3=0%26topic4=0%26topic5=0%26nrp=%26anp=%26idv=7328%26sir=%26sep=and%26ts=0%26dat1=20-12-2024%26dat2=22-09-2025%26ord=0%26pag=1000%26idl=1%26pags=1%22%3ERezultate%3C/a%3E",
          "description": "Dezbaterea Proiectului de Lege pentru modificarea şi completarea Ordonanţei de urgenţă a Guvernului nr. 57/2019 privind Codul administrativ şi pentru modificarea art. 1 alin. (1) din Legea nr. 251/2004 privind unele măsuri referitoare la bunurile primite cu titlu gratuit cu prilejul unor acţiuni de protocol în exercitarea mandatului sau a funcţiei (PL-x 80/2025) (rămas pentru votul final)."
        },
        {
          "fullTextUrl": "https://www.cdep.ro/pls/steno/steno2015.stenograma?ids=8877&idm=14&idl=1",
          "relevantSectionUrl": "https://www.cdep.ro/pls/steno/steno2015.stenograma?ids=8877&idm=14&sir=&sep=and&idv=7328&idl=1&nav=%3Ca%20href=%22/pls/steno/steno2015.cautare%3Fcam=%26com=0%26leg=%26topic1=0%26topic2=0%26topic3=0%26topic4=0%26topic5=0%26nrp=%26anp=%26idv=7328%26sir=%26sep=and%26ts=0%26dat1=20-12-2024%26dat2=22-09-2025%26ord=0%26pag=1000%26idl=1%22%3EInterogare%3C/a%3E%20%26gt%20%3Ca%20href=%22/pls/steno/steno2015.lista%3Fcam=%26com=0%26leg=%26topic1=0%26topic2=0%26topic3=0%26topic4=0%26topic5=0%26nrp=%26anp=%26idv=7328%26sir=%26sep=and%26ts=0%26dat1=20-12-2024%26dat2=22-09-2025%26ord=0%26pag=1000%26idl=1%26pags=1%22%3ERezultate%3C/a%3E",
          "description": "Supunerea la votul final a:"
        },
        {
          "fullTextUrl": "https://www.cdep.ro/pls/steno/steno2015.stenograma?ids=8877&idm=14,007&idl=1",
          "relevantSectionUrl": "https://www.cdep.ro/pls/steno/steno2015.stenograma?ids=8877&idm=14,007&sir=&sep=and&idv=7328&idl=1&nav=%3Ca%20href=%22/pls/steno/steno2015.cautare%3Fcam=%26com=0%26leg=%26topic1=0%26topic2=0%26topic3=0%26topic4=0%26topic5=0%26nrp=%26anp=%26idv=7328%26sir=%26sep=and%26ts=0%26dat1=20-12-2024%26dat2=22-09-2025%26ord=0%26pag=1000%26idl=1%22%3EInterogare%3C/a%3E%20%26gt%20%3Ca%20href=%22/pls/steno/steno2015.lista%3Fcam=%26com=0%26leg=%26topic1=0%26topic2=0%26topic3=0%26topic4=0%26topic5=0%26nrp=%26anp=%26idv=7328%26sir=%26sep=and%26ts=0%26dat1=20-12-2024%26dat2=22-09-2025%26ord=0%26pag=1000%26idl=1%26pags=1%22%3ERezultate%3C/a%3E",
          "description": "Proiectului de Lege privind aprobarea Politicii publice de proprietate privată a statului (PL-x 79/2025) (adoptat);"
        }
      ]
    },
    {
      "ids": "8864",
      "idv": "7328",
      "idm": "298",
      "date": "2025-02-28T00:00:00.000Z",
      "title": "Sedinta comuna a Camerei Deputatilor si Senatului din 28 februarie  2025",
      "link": "https://www.cdep.ro/pls/steno/steno2015.sumar?ids=8864&idl=1",
      "transcripts": [
        {
          "fullTextUrl": "https://www.cdep.ro/pls/steno/steno2015.stenograma?ids=8864&idm=3&idl=1",
          "relevantSectionUrl": "https://www.cdep.ro/pls/steno/steno2015.stenograma?ids=8864&idm=3&sir=&sep=and&idv=7328&idl=1&nav=%3Ca%20href=%22/pls/steno/steno2015.cautare%3Fcam=%26com=0%26leg=%26topic1=0%26topic2=0%26topic3=0%26topic4=0%26topic5=0%26nrp=%26anp=%26idv=7328%26sir=%26sep=and%26ts=0%26dat1=20-12-2024%26dat2=22-09-2025%26ord=0%26pag=1000%26idl=1%22%3EInterogare%3C/a%3E%20%26gt%20%3Ca%20href=%22/pls/steno/steno2015.lista%3Fcam=%26com=0%26leg=%26topic1=0%26topic2=0%26topic3=0%26topic4=0%26topic5=0%26nrp=%26anp=%26idv=7328%26sir=%26sep=and%26ts=0%26dat1=20-12-2024%26dat2=22-09-2025%26ord=0%26pag=1000%26idl=1%26pags=1%22%3ERezultate%3C/a%3E",
          "description": "Dezbaterea şi adoptarea Proiectului de hotărâre privind revocarea din funcţie a preşedintelui Autorităţii Electorale Permanente."
        }
      ]
    },
    {
      "ids": "8857",
      "idv": "7328",
      "idm": "298",
      "date": "2025-02-24T00:00:00.000Z",
      "title": "Sedinta Camerei Deputatilor din 24 februarie  2025",
      "link": "https://www.cdep.ro/pls/steno/steno2015.sumar?ids=8857&idl=1",
      "transcripts": [
        {
          "fullTextUrl": "https://www.cdep.ro/pls/steno/steno2015.stenograma?ids=8857&idm=7&idl=1",
          "relevantSectionUrl": "https://www.cdep.ro/pls/steno/steno2015.stenograma?ids=8857&idm=7&sir=&sep=and&idv=7328&idl=1&nav=%3Ca%20href=%22/pls/steno/steno2015.cautare%3Fcam=%26com=0%26leg=%26topic1=0%26topic2=0%26topic3=0%26topic4=0%26topic5=0%26nrp=%26anp=%26idv=7328%26sir=%26sep=and%26ts=0%26dat1=20-12-2024%26dat2=22-09-2025%26ord=0%26pag=1000%26idl=1%22%3EInterogare%3C/a%3E%20%26gt%20%3Ca%20href=%22/pls/steno/steno2015.lista%3Fcam=%26com=0%26leg=%26topic1=0%26topic2=0%26topic3=0%26topic4=0%26topic5=0%26nrp=%26anp=%26idv=7328%26sir=%26sep=and%26ts=0%26dat1=20-12-2024%26dat2=22-09-2025%26ord=0%26pag=1000%26idl=1%26pags=1%22%3ERezultate%3C/a%3E",
          "description": "Dezbaterea Proiectului de Lege pentru modificarea Ordonanţei Guvernului nr. 41/1994 privind autorizarea plăţii cotizaţiilor la organizaţiile internaţionale interguvernamentale la care România este parte, precum şi pentru modificarea şi completarea Legii nr. 262/2015 pentru aprobarea plăţii contribuţiilor Ministerului Justiţiei şi Ministerului Public la organisme internaţionale, precum şi pentru modificarea şi completarea Ordonanţei Guvernului nr. 41/1994 privind autorizarea plăţii cotizaţiilor la organizaţiile internaţionale interguvernamentale la care România este parte (PL-x 412/2024) (rămas pentru votul final)."
        }
      ]
    },
    {
      "ids": "8856",
      "idv": "7328",
      "idm": "298",
      "date": "2025-02-19T00:00:00.000Z",
      "title": "Sedinta Camerei Deputatilor din 19 februarie  2025",
      "link": "https://www.cdep.ro/pls/steno/steno2015.sumar?ids=8856&idl=1",
      "transcripts": [
        {
          "fullTextUrl": "https://www.cdep.ro/pls/steno/steno2015.stenograma?ids=8856&idm=8&idl=1",
          "relevantSectionUrl": "https://www.cdep.ro/pls/steno/steno2015.stenograma?ids=8856&idm=8&sir=&sep=and&idv=7328&idl=1&nav=%3Ca%20href=%22/pls/steno/steno2015.cautare%3Fcam=%26com=0%26leg=%26topic1=0%26topic2=0%26topic3=0%26topic4=0%26topic5=0%26nrp=%26anp=%26idv=7328%26sir=%26sep=and%26ts=0%26dat1=20-12-2024%26dat2=22-09-2025%26ord=0%26pag=1000%26idl=1%22%3EInterogare%3C/a%3E%20%26gt%20%3Ca%20href=%22/pls/steno/steno2015.lista%3Fcam=%26com=0%26leg=%26topic1=0%26topic2=0%26topic3=0%26topic4=0%26topic5=0%26nrp=%26anp=%26idv=7328%26sir=%26sep=and%26ts=0%26dat1=20-12-2024%26dat2=22-09-2025%26ord=0%26pag=1000%26idl=1%26pags=1%22%3ERezultate%3C/a%3E",
          "description": "Dezbaterea Proiectului de Lege privind desfăşurarea pe timp de pace a misiunilor şi operaţiilor militare pe teritoriul statului român (PL-x 5/2025) (rămas pentru votul final)."
        },
        {
          "fullTextUrl": "https://www.cdep.ro/pls/steno/steno2015.stenograma?ids=8856&idm=9&idl=1",
          "relevantSectionUrl": "https://www.cdep.ro/pls/steno/steno2015.stenograma?ids=8856&idm=9&sir=&sep=and&idv=7328&idl=1&nav=%3Ca%20href=%22/pls/steno/steno2015.cautare%3Fcam=%26com=0%26leg=%26topic1=0%26topic2=0%26topic3=0%26topic4=0%26topic5=0%26nrp=%26anp=%26idv=7328%26sir=%26sep=and%26ts=0%26dat1=20-12-2024%26dat2=22-09-2025%26ord=0%26pag=1000%26idl=1%22%3EInterogare%3C/a%3E%20%26gt%20%3Ca%20href=%22/pls/steno/steno2015.lista%3Fcam=%26com=0%26leg=%26topic1=0%26topic2=0%26topic3=0%26topic4=0%26topic5=0%26nrp=%26anp=%26idv=7328%26sir=%26sep=and%26ts=0%26dat1=20-12-2024%26dat2=22-09-2025%26ord=0%26pag=1000%26idl=1%26pags=1%22%3ERezultate%3C/a%3E",
          "description": "Dezbaterea Proiectului de Lege privind controlul utilizării spaţiului aerian naţional (PL-x 6/2025) (rămas pentru votul final)."
        },
        {
          "fullTextUrl": "https://www.cdep.ro/pls/steno/steno2015.stenograma?ids=8856&idm=11&idl=1",
          "relevantSectionUrl": "https://www.cdep.ro/pls/steno/steno2015.stenograma?ids=8856&idm=11&sir=&sep=and&idv=7328&idl=1&nav=%3Ca%20href=%22/pls/steno/steno2015.cautare%3Fcam=%26com=0%26leg=%26topic1=0%26topic2=0%26topic3=0%26topic4=0%26topic5=0%26nrp=%26anp=%26idv=7328%26sir=%26sep=and%26ts=0%26dat1=20-12-2024%26dat2=22-09-2025%26ord=0%26pag=1000%26idl=1%22%3EInterogare%3C/a%3E%20%26gt%20%3Ca%20href=%22/pls/steno/steno2015.lista%3Fcam=%26com=0%26leg=%26topic1=0%26topic2=0%26topic3=0%26topic4=0%26topic5=0%26nrp=%26anp=%26idv=7328%26sir=%26sep=and%26ts=0%26dat1=20-12-2024%26dat2=22-09-2025%26ord=0%26pag=1000%26idl=1%26pags=1%22%3ERezultate%3C/a%3E",
          "description": "Supunerea la votul final a:"
        },
        {
          "fullTextUrl": "https://www.cdep.ro/pls/steno/steno2015.stenograma?ids=8856&idm=11,012&idl=1",
          "relevantSectionUrl": "https://www.cdep.ro/pls/steno/steno2015.stenograma?ids=8856&idm=11,012&sir=&sep=and&idv=7328&idl=1&nav=%3Ca%20href=%22/pls/steno/steno2015.cautare%3Fcam=%26com=0%26leg=%26topic1=0%26topic2=0%26topic3=0%26topic4=0%26topic5=0%26nrp=%26anp=%26idv=7328%26sir=%26sep=and%26ts=0%26dat1=20-12-2024%26dat2=22-09-2025%26ord=0%26pag=1000%26idl=1%22%3EInterogare%3C/a%3E%20%26gt%20%3Ca%20href=%22/pls/steno/steno2015.lista%3Fcam=%26com=0%26leg=%26topic1=0%26topic2=0%26topic3=0%26topic4=0%26topic5=0%26nrp=%26anp=%26idv=7328%26sir=%26sep=and%26ts=0%26dat1=20-12-2024%26dat2=22-09-2025%26ord=0%26pag=1000%26idl=1%26pags=1%22%3ERezultate%3C/a%3E",
          "description": "Proiectului de Lege privind desfăşurarea pe timp de pace a misiunilor şi operaţiilor militare pe teritoriul statului român (PL-x 5/2025) (adoptat);"
        },
        {
          "fullTextUrl": "https://www.cdep.ro/pls/steno/steno2015.stenograma?ids=8856&idm=11,004&idl=1",
          "relevantSectionUrl": "https://www.cdep.ro/pls/steno/steno2015.stenograma?ids=8856&idm=11,004&sir=&sep=and&idv=7328&idl=1&nav=%3Ca%20href=%22/pls/steno/steno2015.cautare%3Fcam=%26com=0%26leg=%26topic1=0%26topic2=0%26topic3=0%26topic4=0%26topic5=0%26nrp=%26anp=%26idv=7328%26sir=%26sep=and%26ts=0%26dat1=20-12-2024%26dat2=22-09-2025%26ord=0%26pag=1000%26idl=1%22%3EInterogare%3C/a%3E%20%26gt%20%3Ca%20href=%22/pls/steno/steno2015.lista%3Fcam=%26com=0%26leg=%26topic1=0%26topic2=0%26topic3=0%26topic4=0%26topic5=0%26nrp=%26anp=%26idv=7328%26sir=%26sep=and%26ts=0%26dat1=20-12-2024%26dat2=22-09-2025%26ord=0%26pag=1000%26idl=1%26pags=1%22%3ERezultate%3C/a%3E",
          "description": "Propunerii legislative pentru completarea Ordonanţei Guvernului nr. 25/2014 privind încadrarea în muncă şi detaşarea străinilor pe teritoriul României şi pentru modificarea şi completarea unor acte normative privind regimul străinilor în România (Pl-x 494/2018) (respinsă);"
        }
      ]
    },
    {
      "ids": "8853",
      "idv": "7328",
      "idm": "298",
      "date": "2025-02-17T00:00:00.000Z",
      "title": "Sedinta Camerei Deputatilor din 17 februarie  2025",
      "link": "https://www.cdep.ro/pls/steno/steno2015.sumar?ids=8853&idl=1",
      "transcripts": [
        {
          "fullTextUrl": "https://www.cdep.ro/pls/steno/steno2015.stenograma?ids=8853&idm=8&idl=1",
          "relevantSectionUrl": "https://www.cdep.ro/pls/steno/steno2015.stenograma?ids=8853&idm=8&sir=&sep=and&idv=7328&idl=1&nav=%3Ca%20href=%22/pls/steno/steno2015.cautare%3Fcam=%26com=0%26leg=%26topic1=0%26topic2=0%26topic3=0%26topic4=0%26topic5=0%26nrp=%26anp=%26idv=7328%26sir=%26sep=and%26ts=0%26dat1=20-12-2024%26dat2=22-09-2025%26ord=0%26pag=1000%26idl=1%22%3EInterogare%3C/a%3E%20%26gt%20%3Ca%20href=%22/pls/steno/steno2015.lista%3Fcam=%26com=0%26leg=%26topic1=0%26topic2=0%26topic3=0%26topic4=0%26topic5=0%26nrp=%26anp=%26idv=7328%26sir=%26sep=and%26ts=0%26dat1=20-12-2024%26dat2=22-09-2025%26ord=0%26pag=1000%26idl=1%26pags=1%22%3ERezultate%3C/a%3E",
          "description": "Dezbaterea Propunerii legislative pentru completarea Ordonanţei Guvernului nr. 25/2014 privind încadrarea în muncă şi detaşarea străinilor pe teritoriul României şi pentru modificarea şi completarea unor acte normative privind regimul străinilor în România (Pl-x 494/2018) (rămasă pentru votul final)."
        }
      ]
    },
    {
      "ids": "8852",
      "idv": "7328",
      "idm": "298",
      "date": "2025-02-12T00:00:00.000Z",
      "title": "Sedinta Camerei Deputatilor din 12 februarie  2025",
      "link": "https://www.cdep.ro/pls/steno/steno2015.sumar?ids=8852&idl=1",
      "transcripts": [
        {
          "fullTextUrl": "https://www.cdep.ro/pls/steno/steno2015.stenograma?ids=8852&idm=8&idl=1",
          "relevantSectionUrl": "https://www.cdep.ro/pls/steno/steno2015.stenograma?ids=8852&idm=8&sir=&sep=and&idv=7328&idl=1&nav=%3Ca%20href=%22/pls/steno/steno2015.cautare%3Fcam=%26com=0%26leg=%26topic1=0%26topic2=0%26topic3=0%26topic4=0%26topic5=0%26nrp=%26anp=%26idv=7328%26sir=%26sep=and%26ts=0%26dat1=20-12-2024%26dat2=22-09-2025%26ord=0%26pag=1000%26idl=1%22%3EInterogare%3C/a%3E%20%26gt%20%3Ca%20href=%22/pls/steno/steno2015.lista%3Fcam=%26com=0%26leg=%26topic1=0%26topic2=0%26topic3=0%26topic4=0%26topic5=0%26nrp=%26anp=%26idv=7328%26sir=%26sep=and%26ts=0%26dat1=20-12-2024%26dat2=22-09-2025%26ord=0%26pag=1000%26idl=1%26pags=1%22%3ERezultate%3C/a%3E",
          "description": "Supunerea la votul final a:"
        },
        {
          "fullTextUrl": "https://www.cdep.ro/pls/steno/steno2015.stenograma?ids=8852&idm=8,014&idl=1",
          "relevantSectionUrl": "https://www.cdep.ro/pls/steno/steno2015.stenograma?ids=8852&idm=8,014&sir=&sep=and&idv=7328&idl=1&nav=%3Ca%20href=%22/pls/steno/steno2015.cautare%3Fcam=%26com=0%26leg=%26topic1=0%26topic2=0%26topic3=0%26topic4=0%26topic5=0%26nrp=%26anp=%26idv=7328%26sir=%26sep=and%26ts=0%26dat1=20-12-2024%26dat2=22-09-2025%26ord=0%26pag=1000%26idl=1%22%3EInterogare%3C/a%3E%20%26gt%20%3Ca%20href=%22/pls/steno/steno2015.lista%3Fcam=%26com=0%26leg=%26topic1=0%26topic2=0%26topic3=0%26topic4=0%26topic5=0%26nrp=%26anp=%26idv=7328%26sir=%26sep=and%26ts=0%26dat1=20-12-2024%26dat2=22-09-2025%26ord=0%26pag=1000%26idl=1%26pags=1%22%3ERezultate%3C/a%3E",
          "description": "Propunerii legislative pentru modificarea Ordonanţei nr. 25/2014 privind încadrarea în muncă şi detaşarea străinilor pe teritoriul României şi pentru modificarea şi completarea unor acte normative privind regimul străinilor în România (Pl-x 479/2018) (respinsă);"
        }
      ]
    },
    {
      "ids": "8855",
      "idv": "7328",
      "idm": "298",
      "date": "2025-02-05T00:00:00.000Z",
      "title": "Sedinta comuna a Camerei Deputatilor si Senatului din 5 februarie  2025",
      "link": "https://www.cdep.ro/pls/steno/steno2015.sumar?ids=8855&idl=1",
      "transcripts": [
        {
          "fullTextUrl": "https://www.cdep.ro/pls/steno/steno2015.stenograma?ids=8855&idm=2&idl=1",
          "relevantSectionUrl": "https://www.cdep.ro/pls/steno/steno2015.stenograma?ids=8855&idm=2&sir=&sep=and&idv=7328&idl=1&nav=%3Ca%20href=%22/pls/steno/steno2015.cautare%3Fcam=%26com=0%26leg=%26topic1=0%26topic2=0%26topic3=0%26topic4=0%26topic5=0%26nrp=%26anp=%26idv=7328%26sir=%26sep=and%26ts=0%26dat1=20-12-2024%26dat2=22-09-2025%26ord=0%26pag=1000%26idl=1%22%3EInterogare%3C/a%3E%20%26gt%20%3Ca%20href=%22/pls/steno/steno2015.lista%3Fcam=%26com=0%26leg=%26topic1=0%26topic2=0%26topic3=0%26topic4=0%26topic5=0%26nrp=%26anp=%26idv=7328%26sir=%26sep=and%26ts=0%26dat1=20-12-2024%26dat2=22-09-2025%26ord=0%26pag=1000%26idl=1%26pags=1%22%3ERezultate%3C/a%3E",
          "description": "Dezbaterea şi adoptarea Proiectului Legii bugetului de stat pe anul 2025. (L13/2025, PL-x 1/2025)"
        }
      ]
    },
    {
      "ids": "8845",
      "idv": "7328",
      "idm": "298",
      "date": "2025-02-03T00:00:00.000Z",
      "title": "Sedinta Camerei Deputatilor din 3 februarie  2025",
      "link": "https://www.cdep.ro/pls/steno/steno2015.sumar?ids=8845&idl=1",
      "transcripts": [
        {
          "fullTextUrl": "https://www.cdep.ro/pls/steno/steno2015.stenograma?ids=8845&idm=16&idl=1",
          "relevantSectionUrl": "https://www.cdep.ro/pls/steno/steno2015.stenograma?ids=8845&idm=16&sir=&sep=and&idv=7328&idl=1&nav=%3Ca%20href=%22/pls/steno/steno2015.cautare%3Fcam=%26com=0%26leg=%26topic1=0%26topic2=0%26topic3=0%26topic4=0%26topic5=0%26nrp=%26anp=%26idv=7328%26sir=%26sep=and%26ts=0%26dat1=20-12-2024%26dat2=22-09-2025%26ord=0%26pag=1000%26idl=1%22%3EInterogare%3C/a%3E%20%26gt%20%3Ca%20href=%22/pls/steno/steno2015.lista%3Fcam=%26com=0%26leg=%26topic1=0%26topic2=0%26topic3=0%26topic4=0%26topic5=0%26nrp=%26anp=%26idv=7328%26sir=%26sep=and%26ts=0%26dat1=20-12-2024%26dat2=22-09-2025%26ord=0%26pag=1000%26idl=1%26pags=1%22%3ERezultate%3C/a%3E",
          "description": "Dezbaterea Proiectului de Hotărâre privind bugetul Camerei Deputaţilor pe anul 2025 (PHCD 4/2025) (adoptat)."
        }
      ]
    },
    {
      "ids": "8846",
      "idv": "7328",
      "idm": "298",
      "date": "2025-02-03T00:00:00.000Z",
      "title": "Sedinta comuna a Camerei Deputatilor si Senatului din 3 februarie  2025",
      "link": "https://www.cdep.ro/pls/steno/steno2015.sumar?ids=8846&idl=1",
      "transcripts": [
        {
          "fullTextUrl": "https://www.cdep.ro/pls/steno/steno2015.stenograma?ids=8846&idm=2&idl=1",
          "relevantSectionUrl": "https://www.cdep.ro/pls/steno/steno2015.stenograma?ids=8846&idm=2&sir=&sep=and&idv=7328&idl=1&nav=%3Ca%20href=%22/pls/steno/steno2015.cautare%3Fcam=%26com=0%26leg=%26topic1=0%26topic2=0%26topic3=0%26topic4=0%26topic5=0%26nrp=%26anp=%26idv=7328%26sir=%26sep=and%26ts=0%26dat1=20-12-2024%26dat2=22-09-2025%26ord=0%26pag=1000%26idl=1%22%3EInterogare%3C/a%3E%20%26gt%20%3Ca%20href=%22/pls/steno/steno2015.lista%3Fcam=%26com=0%26leg=%26topic1=0%26topic2=0%26topic3=0%26topic4=0%26topic5=0%26nrp=%26anp=%26idv=7328%26sir=%26sep=and%26ts=0%26dat1=20-12-2024%26dat2=22-09-2025%26ord=0%26pag=1000%26idl=1%26pags=1%22%3ERezultate%3C/a%3E",
          "description": "Constituirea unor comisii comune permanente ale Camerei Deputaţilor şi Senatului: - Comisia parlamentară a revoluţionarilor din Decembrie 1989 (vot deschis electronic); - Comisia comună permanentă a Camerei Deputaţilor şi Senatului pentru exercitarea controlului parlamentar asupra activităţii Serviciului Român de Informaţii (vot secret cu buletine de vot); - Comisia parlamentară specială pentru controlul activităţii Serviciului de Informaţii Externe (vot secret cu buletine de vot)."
        }
      ]
    },
    {
      "ids": "8840",
      "idv": "7328",
      "idm": "298",
      "date": "2024-12-21T00:00:00.000Z",
      "title": "Sedinta Camerei Deputatilor din 21 decembrie  2024",
      "link": "https://www.cdep.ro/pls/steno/steno2015.sumar?ids=8840&idl=1",
      "transcripts": [
        {
          "fullTextUrl": "https://www.cdep.ro/pls/steno/steno2015.stenograma?ids=8840&idm=3&idl=1",
          "relevantSectionUrl": "https://www.cdep.ro/pls/steno/steno2015.stenograma?ids=8840&idm=3&sir=&sep=and&idv=7328&idl=1&nav=%3Ca%20href=%22/pls/steno/steno2015.cautare%3Fcam=%26com=0%26leg=%26topic1=0%26topic2=0%26topic3=0%26topic4=0%26topic5=0%26nrp=%26anp=%26idv=7328%26sir=%26sep=and%26ts=0%26dat1=20-12-2024%26dat2=22-09-2025%26ord=0%26pag=1000%26idl=1%22%3EInterogare%3C/a%3E%20%26gt%20%3Ca%20href=%22/pls/steno/steno2015.lista%3Fcam=%26com=0%26leg=%26topic1=0%26topic2=0%26topic3=0%26topic4=0%26topic5=0%26nrp=%26anp=%26idv=7328%26sir=%26sep=and%26ts=0%26dat1=20-12-2024%26dat2=22-09-2025%26ord=0%26pag=1000%26idl=1%26pags=1%22%3ERezultate%3C/a%3E",
          "description": "Depunerea jurământului de credinţă faţă de ţară şi popor de către deputaţi, în şedinţă solemnă."
        }
      ]
    }
  ]
}