{
  "version": "0.1.0",
  "lastUpdated": "2025-09-19T18:07:16.067Z",
  "data": {
    "idp": "21696",
    "title": "Proiect de Lege privind aprobarea Ordonanţei de urgenţă a Guvernului nr.20/2024 pentru modificarea şi completarea Ordonanţei de urgenţă a Guvernului nr.46/2018 privind înfiinţarea, organizarea şi funcţionarea Oficiului Naţional pentru Achiziţii Centralizate",
    "registrationNumber": {
      "bpi": "260/03-04-2024",
      "senateChamber": "L148/2024"
    },
    "legislativeProcedure": "cf. Constitutiei revizuita în 2003",
    "decidingChamber": "Camera Deputaţilor",
    "type": "Proiect de Lege\npentru\naprobarea\nO.U.G. nr.\n20/2024",
    "emergencyProcedure": true,
    "status": {
      "short": "Lege 104/2025LEGE privind aprobarea Ordonantei de urgentă a Guvernului nr. 20/2024 pentru modificarea si completarea Ordonantei de urgentă a Guvernului nr. 46/2018 privind înfiintarea, organizarea si functionarea Oficiului National pentru Achizitii Centralizate",
      "long": "Lege 104/2025LEGE privind aprobarea Ordonantei de urgentă a Guvernului nr. 20/2024 pentru modificarea si completarea Ordonantei de urgentă a Guvernului nr. 46/2018 privind înfiintarea, organizarea si functionarea Oficiului National pentru Achizitii Centralizate"
    },
    "initiators": [
      "GOVERNMENT"
    ],
    "publicConsultation": null,
    "documents": [
      {
        "textUrl": "https://www.cdep.ro/proiecte/2024/200/20/8/em260.pdf",
        "title": "Expunerea de motive"
      },
      {
        "textUrl": "https://www.cdep.ro/proiecte/2024/200/20/8/oug260.pdf",
        "title": "Ordonanţa de urgenţă a Guvernului"
      },
      {
        "textUrl": "https://www.cdep.ro/proiecte/2024/200/20/8/ces260.pdf",
        "title": "Avizul Consiliului Economic şi Social"
      },
      {
        "textUrl": "https://www.cdep.ro/proiecte/2024/200/20/8/cl260.pdf",
        "title": "Avizul Consiliului Legislativ"
      }
    ],
    "url": "https://www.cdep.ro/pls/proiecte/upl_pck2015.proiect?idp=21696"
  }
}