{
  "version": "0.1.0",
  "lastUpdated": "2025-08-12T18:10:17.708Z",
  "data": {
    "idp": "21878",
    "title": "Proiect de Lege pentru modificarea art.197 din Legea nr.286/2009 privind Codul penal",
    "registrationNumber": {
      "bpi": "464/26-06-2024",
      "senateChamber": "L347/2024"
    },
    "legislativeProcedure": "cf. Constitutiei revizuita în 2003",
    "decidingChamber": "Camera Deputaţilor",
    "type": "Proiect de Lege\npentru\nmodificarea\nL. nr.\n286/2009",
    "emergencyProcedure": false,
    "status": {
      "short": "trimis pentru raport la comisiile permanente ale Camerei Deputatilor",
      "long": "trimis pentru raport la comisiile permanente ale Camerei Deputatilor"
    },
    "initiators": [
      "12",
      "28",
      "57"
    ],
    "publicConsultation": null,
    "documents": [
      {
        "textUrl": "https://www.cdep.ro/proiecte/2024/400/10/8/em464.pdf",
        "title": "Expunerea de motive"
      },
      {
        "textUrl": "https://www.cdep.ro/proiecte/2024/400/10/8/ces418.pdf",
        "title": "Avizul Consiliului Economic şi Social"
      },
      {
        "textUrl": "https://www.cdep.ro/proiecte/2024/400/10/8/cl464.pdf",
        "title": "Avizul Consiliului Legislativ"
      },
      {
        "textUrl": "https://www.cdep.ro/proiecte/2024/400/10/8/csm464.pdf",
        "title": "Avizul Consiliului Superior al Magistraturii"
      }
    ],
    "url": "https://www.cdep.ro/pls/proiecte/upl_pck2015.proiect?idp=21878"
  }
}