{
  "version": "0.1.0",
  "lastUpdated": "2025-08-27T00:14:33.306Z",
  "data": {
    "idp": "22174",
    "title": "Proiect de Lege privind aprobarea Ordonanţei de urgenţă a Guvernului nr.133/2024 pentru asigurarea unor împrumuturi din Trezoreria Statului",
    "registrationNumber": {
      "bpi": "777/18-12-2024",
      "senateChamber": "L617/2024"
    },
    "legislativeProcedure": "cf. Constitutiei revizuita în 2003",
    "decidingChamber": "Camera Deputaţilor",
    "type": "Proiect de Lege\npentru\naprobarea\nO.U.G. nr.\n133/2024",
    "emergencyProcedure": true,
    "status": {
      "short": "trimis pentru raport la comisiile permanente ale Camerei Deputatilor",
      "long": "trimis pentru raport la comisiile permanente ale Camerei Deputatilor"
    },
    "initiators": [
      "GOVERNMENT"
    ],
    "publicConsultation": null,
    "documents": [
      {
        "textUrl": "https://www.cdep.ro/proiecte/2025/000/10/0/em777.pdf",
        "title": "Expunerea de motive"
      },
      {
        "textUrl": "https://www.cdep.ro/proiecte/2025/000/10/0/oug777.pdf",
        "title": "Ordonanţa de urgenţă a Guvernului"
      },
      {
        "textUrl": "https://www.cdep.ro/proiecte/2025/000/10/0/cl777.pdf",
        "title": "Avizul Consiliului Legislativ"
      }
    ],
    "url": "https://www.cdep.ro/pls/proiecte/upl_pck2015.proiect?idp=22174"
  }
}