{
  "version": "0.1.0",
  "lastUpdated": "2025-09-07T09:13:52.419Z",
  "data": {
    "idp": "22458",
    "title": "Proiect de Lege pentru modificarea şi completarea Ordonanţei de urgenţă a Guvernului nr.195/2002 privind circulaţia pe drumurile publice",
    "registrationNumber": {
      "bpi": "276/25-06-2025",
      "senateChamber": "L133/2025"
    },
    "legislativeProcedure": "cf. Constitutiei revizuita în 2003",
    "decidingChamber": "Camera Deputaţilor",
    "type": "Proiect de Lege\npentru\nmodificarea\nO.U.G. nr.\n195/2002",
    "emergencyProcedure": false,
    "status": {
      "short": "trimis pentru raport la comisiile permanente ale Camerei Deputatilor",
      "long": "trimis pentru raport la comisiile permanente ale Camerei Deputatilor"
    },
    "initiators": [
      "332",
      "12",
      "26",
      "29",
      "36",
      "44",
      "45",
      "82",
      "90",
      "94",
      "121",
      "125",
      "126",
      "140",
      "149",
      "167",
      "172",
      "181",
      "198",
      "213",
      "236",
      "247",
      "269",
      "285",
      "293",
      "299",
      "314",
      "195",
      "291",
      "4",
      "12",
      "46",
      "64",
      "68",
      "73",
      "80",
      "96",
      "111",
      "112"
    ],
    "publicConsultation": null,
    "documents": [
      {
        "textUrl": "https://www.cdep.ro/proiecte/2025/200/20/1/em276.pdf",
        "title": "Expunerea de motive"
      },
      {
        "textUrl": "https://www.cdep.ro/proiecte/2025/200/20/1/ces276.pdf",
        "title": "Avizul Consiliului Economic şi Social"
      },
      {
        "textUrl": "https://www.cdep.ro/proiecte/2025/200/20/1/cl276.pdf",
        "title": "Avizul Consiliului Legislativ"
      }
    ],
    "url": "https://www.cdep.ro/pls/proiecte/upl_pck2015.proiect?idp=22458"
  }
}